<?xml version="1.0"?>
	<watches> 
		<watch model="GGR8688N1-25551BR" active="1">
			<ul>
				<li>瑞士制造机芯</li>
				<li>6H位日历显示</li>
				<li>不锈钢表壳</li>
				<li>离子电镀玫瑰金</li>
				<li>高级真皮表带</li>
				<li>蓝宝石水晶玻璃表镜</li>
				<li>30米防水</li>
				<li>表壳尺寸：长度47.00毫米，宽度34.40毫米，厚度8.35毫米</li>
			</ul>
		</watch>
		<watch model="BGR8688N1-25551BR" active="1">
			<ul>
				<li>瑞士制造机芯</li>
				<li>6H位日历显示</li>
				<li>不锈钢表壳</li>
				<li>离子电镀玫瑰金</li>
				<li>高级真皮表带</li>
				<li>蓝宝石水晶玻璃表镜</li>
				<li>30米防水</li>
				<li>表壳尺寸：长度43.60毫米，宽度31.50毫米，厚度7.90毫米</li>
			</ul>
		</watch>
		<watch model="LGR8688N1-25551BR" active="1">
			<ul>
				<li>瑞士制造机芯</li>
				<li>6H位日历显示</li>
				<li>不锈钢表壳</li>
				<li>离子电镀玫瑰金</li>
				<li>高级真皮表带</li>
				<li>蓝宝石水晶玻璃表镜</li>
				<li>30米防水</li>
				<li>表壳尺寸：长度35.50毫米，宽度25.00毫米，厚度7.40毫米</li>
			</ul>
		</watch>
		<watch model="GS8688C-2856" active="1">
			<ul>
				<li>瑞士制造计时码表</li>
				<li>日历显示</li>
				<li>1/1/10、60秒和30分钟计时功能</li>
				<li>不锈钢表壳、表带</li>
				<li>蓝宝石水晶玻璃表镜</li>
				<li>30米防水</li>
			</ul>
		</watch>
		<watch model="BS8688-2556" active="1">
			<ul>
				<li>瑞士制造机芯</li>
				<li>小三针</li>
				<li>日历显示</li>
				<li>不锈钢表壳、表带</li>
				<li>蓝宝石水晶玻璃表镜</li>
				<li>30米防水功能</li>
			</ul>
		</watch>
		<watch model="GG8688-2556L" active="0">
			<ul>
				<li>瑞士制造机芯</li>
				<li>两地时间</li>
				<li>24小时显示</li>
				<li>日历显示</li>
				<li>不锈钢表壳、表带</li>
				<li>电镀10微米18K玫瑰金</li>
				<li>高级真皮表带</li>
				<li>蓝宝石水晶玻璃表镜</li>
				<li>30米防水功能</li>
			</ul>
		</watch>
		<watch model="LS8688-2556" active="1">
			<ul>
				<li>瑞士制造机芯</li>
				<li>小三针</li>
				<li>不锈钢表壳、表带</li>
				<li>蓝宝石水晶玻璃表镜</li>
				<li>30米防水功能</li>
			</ul>
		</watch>
		<watch model="GS8688C-2853BR" active="1">
			<ul>
				<li>瑞士制造计时码表</li>
				<li>日历显示</li>
				<li>1/10秒、60秒和30分钟计时器</li>
				<li>不锈钢表壳</li>
				<li>天然魔鬼鱼皮表带</li>
				<li>蓝宝石水晶玻璃表镜</li>
				<li>30米防水</li>
			</ul>
		</watch>
		<watch model="GS8688C-2854PR" active="1">
			<ul>
				<li>瑞士制造计时码表</li>
				<li>日历显示</li>
				<li>1/10秒、60秒和30分钟计时器</li>
				<li>不锈钢表壳</li>
				<li>天然魔鬼鱼皮表带</li>
				<li>蓝宝石水晶玻璃表镜</li>
				<li>30米防水</li>
			</ul>
		</watch>
		<watch model="GS8688C-2857RD" active="1">
			<ul>
				<li>瑞士制造计时码表</li>
				<li>日历显示</li>
				<li>1/10秒、60秒和30分钟计时器</li>
				<li>不锈钢表壳</li>
				<li>天然魔鬼鱼皮表带</li>
				<li>蓝宝石水晶玻璃表镜</li>
				<li>30米防水</li>
			</ul>
		</watch>
		<watch model="GG8688N-2556L" active="1">
			<ul>
				<li>瑞士制造机芯</li>
				<li>指针式日历</li>
				<li>指针式周历</li>
				<li>月相显示</li>
				<li>不锈钢表壳</li>
				<li>电镀10微米18K玫瑰金</li>
				<li>高级真皮表带</li>
				<li>蓝宝石水晶玻璃表镜</li>
				<li>30米防水</li>
			</ul>
		</watch>
		<watch model="BG8688-2556L" active="1">
			<ul>
				<li>瑞士制造机芯</li>
				<li>小三针</li>
				<li>日历显示</li>
				<li>不锈钢表壳</li>
				<li>电镀10微米18K玫瑰金</li>
				<li>高级真皮表带</li>
				<li>蓝宝石水晶玻璃表镜</li>
				<li>30米防水功能</li>
			</ul>
		</watch>
		<watch model="LG8688-2556L" active="1">
			<ul>
				<li>瑞士制造机芯</li>
				<li>小三针</li>
				<li>不锈钢表壳</li>
				<li>电镀10微米18K玫瑰金</li>
				<li>高级真皮表带</li>
				<li>蓝宝石水晶玻璃表镜</li>
				<li>30米防水功能</li>
			</ul>
		</watch>
</watches> 
